MANIFEST.in
README.md
ncplugin.py
setup.py
NCPlugin.egg-info/PKG-INFO
NCPlugin.egg-info/SOURCES.txt
NCPlugin.egg-info/dependency_links.txt
NCPlugin.egg-info/entry_points.txt
NCPlugin.egg-info/requires.txt
NCPlugin.egg-info/top_level.txt