Metadata-Version: 1.0
Name: NCPlugin
Version: 0.4
Summary: Nose plugin to raise an OS X Notification Center alert when a test run has finished
Home-page: https://github.com/dreynolds/nose-notification-centre
Author: David Reynolds
Author-email: david@reynoldsfamily.org.uk
License: GNU LGPL
Platform: MacOS X
